ai_helpers/core.py
ai_helpers/init.py
ai_helpers/utils.py
ai_helpers_fercinent-0.0.1.dist-info/METADATA
ai_helpers_fercinent-0.0.1.dist-info/WHEEL
ai_helpers_fercinent-0.0.1.dist-info/top_level.txt
ai_helpers_fercinent-0.0.1.dist-info/RECORD
