Metadata-Version: 2.4
Name: ai-helpers-fercinent
Version: 0.0.1
Summary: A helper library for AI-powered Python applications
Author-email: Fercinent Thomas <your-email@example.com>
Requires-Python: >=3.8
Requires-Dist: requests
